sweat/__init__.py
sweat/constants.py
sweat/examples/data/2020-06-01-16-52-40.fit
sweat/examples/data/3173437224.tcx
sweat/examples/data/4078723797.fit
sweat/examples/data/4078723797_strava.gpx
sweat/examples/data/4801048867.fit
sweat/examples/data/4801048867_strava.gpx
sweat/examples/data/6449921903_ACTIVITY.fit
sweat/examples/data/6471559601_ACTIVITY.fit
sweat/examples/data/activity_4078723797.gpx
sweat/examples/data/activity_4078723797.tcx
sweat/examples/data/activity_4801048867.gpx
sweat/examples/data/activity_4801048867.tcx
sweat/examples/data/activity_5039744860.gpx
sweat/examples/data/activity_5039744860.tcx
sweat/examples/index.yml
sweat/examples/utils.py
sweat/hrm/__init__.py
sweat/hrm/heartrate_models.py
sweat/io/__init__.py
sweat/io/exceptions.py
sweat/io/fit.py
sweat/io/fit_profile.json
sweat/io/generic.py
sweat/io/gpx.py
sweat/io/models.py
sweat/io/strava.py
sweat/io/tcx.py
sweat/io/utils.py
sweat/metrics/__init__.py
sweat/metrics/core.py
sweat/metrics/heartrate.py
sweat/metrics/location.py
sweat/metrics/power.py
sweat/metrics/speed.py
sweat/pandas.py
sweat/pdm/__init__.py
sweat/pdm/regressors.py
sweat/pdm/w_prime_balance.py
sweat/utils.py
sweat-0.25.0.dist-info/LICENSE
sweat-0.25.0.dist-info/WHEEL
sweat-0.25.0.dist-info/METADATA
sweat-0.25.0.dist-info/RECORD
