Metadata-Version: 2.1
Name: sweat
Version: 0.25.0
Summary: Workout analysis
Home-page: https://github.com/goldencheetah/sweatpy
License: MIT
Author: Aart Goossens
Author-email: aart@goossens.me
Requires-Python: >=3.6.1,<4.0.0
Classifier: License :: OSI Approved :: MIT License
Classifier: Programming Language :: Python :: 3
Classifier: Programming Language :: Python :: 3.7
Classifier: Programming Language :: Python :: 3.8
Classifier: Programming Language :: Python :: 3.9
Requires-Dist: fitparse (>=1.1.0,<2.0.0)
Requires-Dist: lmfit (>=1.0.0,<2.0.0)
Requires-Dist: matplotlib (>=3.3.4,<4.0.0)
Requires-Dist: pandas (>=1.0.3,<2.0.0)
Requires-Dist: pydantic (>=1.4,<2.0)
Requires-Dist: pyyaml (>=6.0.0,<7.0.0)
Requires-Dist: requests (>=2.23.0,<3.0.0)
Requires-Dist: scikit-learn (>=0.23.1)
Requires-Dist: scipy (>=1.4.1,<2.0.0)
Requires-Dist: stravalib (>=0.10.2,<0.11.0)
Project-URL: Documentation, https://github.com/goldencheetah/sweatpy
Project-URL: Repository, https://github.com/goldencheetah/sweatpy
